polyvalid/__init__.py
polyvalid/py.typed
polyvalid/bindings/__init__.py
polyvalid/bindings/polyvalid/__init__.py
polyvalid/bindings/polyvalid/bindings.py
polyvalid/bindings/polyvalid/polyvalid.wasm
polyvalid-0.1.7.dist-info/METADATA
polyvalid-0.1.7.dist-info/WHEEL
polyvalid-0.1.7.dist-info/top_level.txt
polyvalid-0.1.7.dist-info/RECORD
