Metadata-Version: 2.1
Name: polyvalid
Version: 0.1.7
Summary: A validator for package names, namespace, username and app name on wasmer
Requires-Dist: wasmer
Requires-Dist: wasmer-compiler-cranelift
